image_tools/__init__.py
image_tools/downloader.py
image_tools/version.py
tests/__init__.py
tests/test_downloader.py
python_image_tools-0.4.dist-info/LICENSE
python_image_tools-0.4.dist-info/METADATA
python_image_tools-0.4.dist-info/WHEEL
python_image_tools-0.4.dist-info/top_level.txt
python_image_tools-0.4.dist-info/RECORD
