Metadata-Version: 2.1
Name: python-image-tools
Version: 0.4
Summary: python-image-tools is a python package for working with images
Home-page: https://github.com/amirhamiri/python-image-tools
Author: Amirhossein Amiri
Author-email: amirhamiri74@gmail.com
License: MIT
Download-URL: https://github.com/amirhamiri/python-image-tools/archive/0.4.tar.gz
Project-URL: Documentation, https://github.com/amirhamiri/python-image-tools#readme
Project-URL: Issues, https://github.com/amirhamiri/python-image-tools/issues
Keywords: image,download,python,resize
Platform: UNKNOWN
Classifier: Development Status :: 5 - Production/Stable
Classifier: Intended Audience :: Developers
Classifier: License :: OSI Approved :: MIT License
Classifier: Natural Language :: English
Classifier: Operating System :: OS Independent
Classifier: Programming Language :: Python :: 3
Classifier: Programming Language :: Python :: 3.4
Classifier: Programming Language :: Python :: 3.5
Classifier: Programming Language :: Python :: 3.6
Classifier: Programming Language :: Python :: 3.7
Classifier: Programming Language :: Python :: 3.8
Classifier: Programming Language :: Python :: 3.9
Classifier: Programming Language :: Python :: 3.10
Classifier: Topic :: Software Development :: Build Tools
License-File: LICENSE
Requires-Dist: Pillow (==9.4.0)
Requires-Dist: requests (==2.28.2)
